{
    "configurations": [
        {
            "name": "Linux",
            "includePath": [
                "${workspaceFolder}/**",
                "${workspaceFolder}/main/inc/**",
                "${workspaceFolder}/main/src/**",
                "${workspaceFolder}/main/**",
                "/usr/local/include/opencv4/**",
                "/opt/qt/5.12.9/gcc_64/include/**"
            ],
            "defines": [],
            "compilerPath": "/usr/lib/ccache/gcc",
            "cStandard": "c17",
            "cppStandard": "gnu++14",
            "intelliSenseMode": "linux-gcc-x64"
        }
    ],
    "version": 4
}